{"experimentVersion":"micro_debug","participantID":"t","participantAge":"t","participantGender":2,"confirmationCode":"0097386","participantFeedback":"","totalTrials":13,"dataRecordFrequency":0.03999999910593033,"restbreakDuration":5.0,"getReadyDuration":5.0,"trialList":[0,1,2,3,4,5,6,7,8,9,10,11,12],"allTrialData":[{"trialNumber":0,"trialListIndex":[0],"mapName":"Persistent","doubleRewardTask":false,"rewardType":"","starLocation":{"x":0.0,"y":0.0,"z":0.0},"trialAnswer":"","trialQuestion":"","possibleTrialAnswers":[],"preDisplayCueTime":1.5,"displayCueTime":2.0,"goCueDelay":1.5,"minDwellAtReward":0.10000000149011612,"displayMessageTime":1.5,"errorDwellTime":1.5,"goalHitPauseTime":1.0,"finalGoalHitPauseTime":2.0,"pausePriorFeedbackTime":0.5,"feedbackFlashDuration":1.0,"trialScore":0.0,"maxResponseTime":10.0,"responseTime":[0.0],"responseChoice":[""],"FLAG_trialTimeout":[false],"FLAG_trialError":[false]},{"trialNumber":1,"trialListIndex":[1],"mapName":"InformationScreen","doubleRewardTask":false,"rewardType":"","starLocation":{"x":0.0,"y":0.0,"z":0.0},"trialAnswer":"","trialQuestion":"","possibleTrialAnswers":[],"preDisplayCueTime":1.5,"displayCueTime":2.0,"goCueDelay":1.5,"minDwellAtReward":0.10000000149011612,"displayMessageTime":1.5,"errorDwellTime":1.5,"goalHitPauseTime":1.0,"finalGoalHitPauseTime":2.0,"pausePriorFeedbackTime":0.5,"feedbackFlashDuration":1.0,"trialScore":0.0,"maxResponseTime":10.0,"responseTime":[0.0],"responseChoice":[""],"FLAG_trialTimeout":[false],"FLAG_trialError":[false]},{"trialNumber":2,"trialListIndex":[2],"mapName":"BeforeStartingScreen","doubleRewardTask":false,"rewardType":"","starLocation":{"x":0.0,"y":0.0,"z":0.0},"trialAnswer":"","trialQuestion":"","possibleTrialAnswers":[],"preDisplayCueTime":1.5,"displayCueTime":2.0,"goCueDelay":1.5,"minDwellAtReward":0.10000000149011612,"displayMessageTime":1.5,"errorDwellTime":1.5,"goalHitPauseTime":1.0,"finalGoalHitPauseTime":2.0,"pausePriorFeedbackTime":0.5,"feedbackFlashDuration":1.0,"trialScore":0.0,"maxResponseTime":10.0,"responseTime":[0.0],"responseChoice":[""],"FLAG_trialTimeout":[false],"FLAG_trialError":[false]},{"trialNumber":3,"trialListIndex":[3],"mapName":"ConsentScreen","doubleRewardTask":false,"rewardType":"","starLocation":{"x":0.0,"y":0.0,"z":0.0},"trialAnswer":"","trialQuestion":"","possibleTrialAnswers":[],"preDisplayCueTime":1.5,"displayCueTime":2.0,"goCueDelay":1.5,"minDwellAtReward":0.10000000149011612,"displayMessageTime":1.5,"errorDwellTime":1.5,"goalHitPauseTime":1.0,"finalGoalHitPauseTime":2.0,"pausePriorFeedbackTime":0.5,"feedbackFlashDuration":1.0,"trialScore":0.0,"maxResponseTime":10.0,"responseTime":[0.0],"responseChoice":[""],"FLAG_trialTimeout":[false],"FLAG_trialError":[false]},{"trialNumber":4,"trialListIndex":[4],"mapName":"StartScreen","doubleRewardTask":false,"rewardType":"","starLocation":{"x":0.0,"y":0.0,"z":0.0},"trialAnswer":"","trialQuestion":"","possibleTrialAnswers":[],"preDisplayCueTime":1.5,"displayCueTime":2.0,"goCueDelay":1.5,"minDwellAtReward":0.10000000149011612,"displayMessageTime":1.5,"errorDwellTime":1.5,"goalHitPauseTime":1.0,"finalGoalHitPauseTime":2.0,"pausePriorFeedbackTime":0.5,"feedbackFlashDuration":1.0,"trialScore":0.0,"maxResponseTime":10.0,"responseTime":[0.0],"responseChoice":[""],"FLAG_trialTimeout":[false],"FLAG_trialError":[false]},{"trialNumber":5,"trialListIndex":[5],"mapName":"InstructionsScreen","doubleRewardTask":false,"rewardType":"","starLocation":{"x":0.0,"y":0.0,"z":0.0},"trialAnswer":"","trialQuestion":"","possibleTrialAnswers":[],"preDisplayCueTime":1.5,"displayCueTime":2.0,"goCueDelay":1.5,"minDwellAtReward":0.10000000149011612,"displayMessageTime":1.5,"errorDwellTime":1.5,"goalHitPauseTime":1.0,"finalGoalHitPauseTime":2.0,"pausePriorFeedbackTime":0.5,"feedbackFlashDuration":1.0,"trialScore":0.0,"maxResponseTime":10.0,"responseTime":[0.0],"responseChoice":[""],"FLAG_trialTimeout":[false],"FLAG_trialError":[false]},{"trialNumber":6,"trialListIndex":[6],"mapName":"Practice","doubleRewardTask":false,"rewardType":"cheese","starLocation":{"x":0.0,"y":0.0,"z":0.0},"trialAnswer":"A","trialQuestion":"","possibleTrialAnswers":[],"preDisplayCueTime":1.5,"displayCueTime":2.0,"goCueDelay":1.5,"minDwellAtReward":0.10000000149011612,"displayMessageTime":1.5,"errorDwellTime":1.5,"goalHitPauseTime":1.0,"finalGoalHitPauseTime":2.0,"pausePriorFeedbackTime":0.5,"feedbackFlashDuration":1.0,"trialScore":0.0,"maxResponseTime":10.0,"responseTime":[1.707320213317871],"responseChoice":["B"],"FLAG_trialTimeout":[false],"FLAG_trialError":[false]},{"trialNumber":7,"trialListIndex":[7],"mapName":"GetReady","doubleRewardTask":false,"rewardType":"","starLocation":{"x":0.0,"y":0.0,"z":0.0},"trialAnswer":"","trialQuestion":"","possibleTrialAnswers":[],"preDisplayCueTime":1.5,"displayCueTime":2.0,"goCueDelay":1.5,"minDwellAtReward":0.10000000149011612,"displayMessageTime":1.5,"errorDwellTime":1.5,"goalHitPauseTime":1.0,"finalGoalHitPauseTime":2.0,"pausePriorFeedbackTime":0.5,"feedbackFlashDuration":1.0,"trialScore":0.0,"maxResponseTime":10.0,"responseTime":[1.707320213317871],"responseChoice":[""],"FLAG_trialTimeout":[false],"FLAG_trialError":[false]},{"trialNumber":8,"trialListIndex":[8],"mapName":"MainTrial","doubleRewardTask":false,"rewardType":"cheese","starLocation":{"x":0.0,"y":0.0,"z":0.0},"trialAnswer":"A","trialQuestion":"","possibleTrialAnswers":[],"preDisplayCueTime":1.5,"displayCueTime":2.0,"goCueDelay":1.5,"minDwellAtReward":0.10000000149011612,"displayMessageTime":1.5,"errorDwellTime":1.5,"goalHitPauseTime":1.0,"finalGoalHitPauseTime":2.0,"pausePriorFeedbackTime":0.5,"feedbackFlashDuration":1.0,"trialScore":10.0,"maxResponseTime":10.0,"responseTime":[3.4285545349121095],"responseChoice":["A"],"FLAG_trialTimeout":[false],"FLAG_trialError":[false]},{"trialNumber":9,"trialListIndex":[9],"mapName":"MainTrial","doubleRewardTask":false,"rewardType":"cheese","starLocation":{"x":0.0,"y":0.0,"z":0.0},"trialAnswer":"A","trialQuestion":"","possibleTrialAnswers":[],"preDisplayCueTime":1.5,"displayCueTime":2.0,"goCueDelay":1.5,"minDwellAtReward":0.10000000149011612,"displayMessageTime":1.5,"errorDwellTime":1.5,"goalHitPauseTime":1.0,"finalGoalHitPauseTime":2.0,"pausePriorFeedbackTime":0.5,"feedbackFlashDuration":1.0,"trialScore":10.0,"maxResponseTime":10.0,"responseTime":[4.7708587646484379],"responseChoice":["A"],"FLAG_trialTimeout":[false],"FLAG_trialError":[false]},{"trialNumber":10,"trialListIndex":[10],"mapName":"MainTrial","doubleRewardTask":false,"rewardType":"cheese","starLocation":{"x":0.0,"y":0.0,"z":0.0},"trialAnswer":"A","trialQuestion":"","possibleTrialAnswers":[],"preDisplayCueTime":1.5,"displayCueTime":2.0,"goCueDelay":1.5,"minDwellAtReward":0.10000000149011612,"displayMessageTime":1.5,"errorDwellTime":1.5,"goalHitPauseTime":1.0,"finalGoalHitPauseTime":2.0,"pausePriorFeedbackTime":0.5,"feedbackFlashDuration":1.0,"trialScore":-5.0,"maxResponseTime":10.0,"responseTime":[0.976837158203125],"responseChoice":["B"],"FLAG_trialTimeout":[false],"FLAG_trialError":[false]},{"trialNumber":0,"trialListIndex":[],"mapName":"","doubleRewardTask":false,"rewardType":"","starLocation":{"x":0.0,"y":0.0,"z":0.0},"trialAnswer":"","trialQuestion":"","possibleTrialAnswers":[],"preDisplayCueTime":1.5,"displayCueTime":2.0,"goCueDelay":1.5,"minDwellAtReward":0.10000000149011612,"displayMessageTime":1.5,"errorDwellTime":1.5,"goalHitPauseTime":1.0,"finalGoalHitPauseTime":2.0,"pausePriorFeedbackTime":0.5,"feedbackFlashDuration":1.0,"trialScore":0.0,"maxResponseTime":10.0,"responseTime":[],"responseChoice":[],"FLAG_trialTimeout":[],"FLAG_trialError":[]},{"trialNumber":0,"trialListIndex":[],"mapName":"Exit","doubleRewardTask":false,"rewardType":"","starLocation":{"x":0.0,"y":0.0,"z":0.0},"trialAnswer":"","trialQuestion":"","possibleTrialAnswers":[],"preDisplayCueTime":1.5,"displayCueTime":2.0,"goCueDelay":1.5,"minDwellAtReward":0.10000000149011612,"displayMessageTime":1.5,"errorDwellTime":1.5,"goalHitPauseTime":1.0,"finalGoalHitPauseTime":2.0,"pausePriorFeedbackTime":0.5,"feedbackFlashDuration":1.0,"trialScore":0.0,"maxResponseTime":10.0,"responseTime":[],"responseChoice":[],"FLAG_trialTimeout":[],"FLAG_trialError":[]}]}